pytest_persistence/XDistScheduling.py
pytest_persistence/__init__.py
pytest_persistence/plugin.py
pytest_persistence-0.1.11.dist-info/LICENSE
pytest_persistence-0.1.11.dist-info/METADATA
pytest_persistence-0.1.11.dist-info/WHEEL
pytest_persistence-0.1.11.dist-info/entry_points.txt
pytest_persistence-0.1.11.dist-info/top_level.txt
pytest_persistence-0.1.11.dist-info/RECORD
