Metadata-Version: 2.1
Name: pytest-persistence
Version: 0.1.11
Summary: Pytest tool for persistent objects
Home-page: https://github.com/JaurbanRH/pytest-persistence
Author: Jakub Urban
Author-email: kubo.urban@gmail.com
Maintainer: Jakub Urban
Classifier: Programming Language :: Python :: 3
Classifier: Programming Language :: Python :: 3.7
Classifier: Operating System :: OS Independent
Classifier: License :: OSI Approved :: MIT License
License-File: LICENSE
